mwconstants/__init__.py
mwconstants/languages.py
mwconstants/links.py
mwconstants/media.py
mwconstants/namespaces.py
mwconstants/constants/__init__.py
mwconstants/constants/c_languages.py
mwconstants/constants/c_media.py
mwconstants/constants/c_namespaces.py
mwconstants-0.1.0.dist-info/LICENSE
mwconstants-0.1.0.dist-info/METADATA
mwconstants-0.1.0.dist-info/WHEEL
mwconstants-0.1.0.dist-info/top_level.txt
mwconstants-0.1.0.dist-info/RECORD
