Metadata-Version: 2.1
Name: mwconstants
Version: 0.1.0
Summary: Various data and utilities for processing wikitext.
Home-page: https://gitlab.wikimedia.org/repos/research/mwconstants
Author: geohci (Isaac Johnson)
Author-email: <isaac@wikimedia.org>
License: MIT License
Keywords: python,wikitext,wiki
Classifier: Development Status :: 4 - Beta
Classifier: License :: OSI Approved :: MIT License
Classifier: Natural Language :: English
Classifier: Programming Language :: Python :: 3
Classifier: Programming Language :: Python :: 3.7
Classifier: Programming Language :: Python :: 3.8
Classifier: Programming Language :: Python :: 3.9
Classifier: Programming Language :: Python :: 3.10
Classifier: Operating System :: Unix
Classifier: Operating System :: MacOS :: MacOS X
Classifier: Operating System :: Microsoft :: Windows
License-File: LICENSE
Requires-Dist: requests
Provides-Extra: dev
Requires-Dist: pytest (>=6.2.5) ; extra == 'dev'
Provides-Extra: tests
Requires-Dist: pytest (>=6.2.5) ; extra == 'tests'
